ReadMe.md
setup.py
ISPIP.egg-info/PKG-INFO
ISPIP.egg-info/SOURCES.txt
ISPIP.egg-info/dependency_links.txt
ISPIP.egg-info/entry_points.txt
ISPIP.egg-info/requires.txt
ISPIP.egg-info/top_level.txt
ispip/__init__.py
ispip/argscontainer.py
ispip/cli_interface.py
ispip/compare_auc_delong_xu.py
ispip/crossvalidation.py
ispip/generate.py
ispip/graphing.py
ispip/ispip.py
ispip/postprocess.py
ispip/predict.py
ispip/preprocess.py
ispip/pymolviz.py
ispip/trainingsetstats.py