Metadata-Version: 2.1
Name: ISPIP
Version: 1.7
Summary: Integrated Structure-based Protein Interface Prediction
Home-page: https://github.com/eved1018/ISPIP
Author: Evan Edelstein
Author-email: edelsteinevan@gmail.com
License: MIT
Platform: UNKNOWN
